ihatepyc/__init__.py
ihatepyc/cli.py
ihatepyc/pycisbad.py
ihatepyc-1.0.0.post1.dist-info/LICENSE
ihatepyc-1.0.0.post1.dist-info/METADATA
ihatepyc-1.0.0.post1.dist-info/WHEEL
ihatepyc-1.0.0.post1.dist-info/entry_points.txt
ihatepyc-1.0.0.post1.dist-info/top_level.txt
ihatepyc-1.0.0.post1.dist-info/RECORD
