Metadata-Version: 2.1
Name: ihatepyc
Version: 1.0.0.post1
Summary: We all hate the __pycache__ folders, so lets delete them
Author: Combo Gang
Author-email: contact@combogang.com
License: MIT
License-File: LICENSE
